{
  "_static": {
    "generator": {
      "name": "@globus/static-search-portal"
    }
  },
  "data": {
    "version": "1.0.0",
    "attributes": {
      "metadata": {
        "title": "LSSTDESC Data Portal"
      },
      "content": {
        "headline": "LSSTDESC Data Portal"
      },
      "features": {
        "transfer": true
      },
      "components": {
        "Result": {
          "heading": "entries[0].content.name",
          "fields": [
            {
              "label": "Summary",
              "property": "entries[0].content.summary"
            },
            {
              "label": "Documentation",
              "property": "entries[0].content.documentation",
              "type": "link"
            },
            {
              "label": "Size",
              "property": "entries[0].content.size"
            },
            {
              "label": "Tags",
              "property": "entries[0].content.tags"
            }
          ]
        },
        "ResultListing": {
          "fields": [
            {
              "label": "Summary",
              "property": "entries[0].content.summary"
            },
            {
              "label": "Documentation",
              "property": "entries[0].content.documentation",
              "type": "link"
            },
            {
              "label": "Size",
              "property": "entries[0].content.size"
            }
          ]
        }
      },
      "globus": {
        "application": {
          "client_id": "8d78919b-1fe1-4663-bedf-ce5f4f7f0ce0"
        },
        "search": {
          "index": "79561f09-e9bc-47e1-bc28-cf3ac415623c",
          "facets": [
            {
              "name": "Tags",
              "field_name": "tags",
              "type": "terms",
              "size": 10
            }
          ]
        }
      }
    }
  }
}
